Metadata-Version: 2.1
Name: KYYdistributions
Version: 1.0
Summary: KYYdistributions
Home-page: UNKNOWN
License: UNKNOWN
Platform: UNKNOWN
